flickr_mirroring-1.0.6.data/scripts/mirror_flickr
mirroring/__init__.py
mirroring/flickr.py
flickr_mirroring-1.0.6.dist-info/METADATA
flickr_mirroring-1.0.6.dist-info/WHEEL
flickr_mirroring-1.0.6.dist-info/top_level.txt
flickr_mirroring-1.0.6.dist-info/RECORD
