Metadata-Version: 2.1
Name: flickr-mirroring
Version: 1.0.6
Summary: Flickr Mirroring
Home-page: UNKNOWN
Author: Daniel CAUNE
Author-email: daniel.caune@gmail.com
License: MIT
Platform: any
Classifier: Development Status :: 5 - Production/Stable
Classifier: License :: OSI Approved :: MIT License
Classifier: Operating System :: OS Independent
Classifier: Programming Language :: Python
Classifier: Topic :: Software Development :: Libraries
Requires-Python: >=3.6
Requires-Dist: flickr-api
Requires-Dist: langdetect
Requires-Dist: pillow
Requires-Dist: perseus-core-library
Requires-Dist: requests
